ensembl_prodinf_djcore-1.2.0.dev2-py3.8-nspkg.pth
ensembl/production/djcore/__init__.py
ensembl/production/djcore/admin.py
ensembl/production/djcore/apps.py
ensembl/production/djcore/config.py
ensembl/production/djcore/fields.py
ensembl/production/djcore/filters.py
ensembl/production/djcore/forms.py
ensembl/production/djcore/models.py
ensembl/production/djcore/tests.py
ensembl/production/djcore/utils.py
ensembl_prodinf_djcore-1.2.0.dev2.dist-info/LICENSE
ensembl_prodinf_djcore-1.2.0.dev2.dist-info/METADATA
ensembl_prodinf_djcore-1.2.0.dev2.dist-info/NOTICE
ensembl_prodinf_djcore-1.2.0.dev2.dist-info/WHEEL
ensembl_prodinf_djcore-1.2.0.dev2.dist-info/namespace_packages.txt
ensembl_prodinf_djcore-1.2.0.dev2.dist-info/top_level.txt
ensembl_prodinf_djcore-1.2.0.dev2.dist-info/RECORD
